smartPID/__init__.py
smartPID/smartPID.py
smartPID-1.0.dist-info/LICENSE.txt
smartPID-1.0.dist-info/METADATA
smartPID-1.0.dist-info/WHEEL
smartPID-1.0.dist-info/top_level.txt
smartPID-1.0.dist-info/RECORD
