Metadata-Version: 2.1
Name: smartPID
Version: 1.0
Summary: This library contains three controller algorithms.
Home-page: https://mvp.aliyun.com/mvp/detail/450?spm=5176.11535038.header.17.4827755fXaDyyW
Author: Qi Zhu
Author-email: 2335666965@qq.com
License: UNKNOWN
Platform: UNKNOWN
Classifier: Programming Language :: Python :: 3
Classifier: License :: OSI Approved :: MIT License
Classifier: Operating System :: OS Independent
